mbari_aidata/.gitignore
mbari_aidata/__init__.py
mbari_aidata/__main__.py
mbari_aidata/commands/db_utils.py
mbari_aidata/commands/download.py
mbari_aidata/commands/embedding_rank.py
mbari_aidata/commands/load_boxes.py
mbari_aidata/commands/load_clusters.py
mbari_aidata/commands/load_common.py
mbari_aidata/commands/load_exemplars.py
mbari_aidata/commands/load_images.py
mbari_aidata/commands/load_queue.py
mbari_aidata/commands/load_tracks.py
mbari_aidata/commands/load_video.py
mbari_aidata/commands/split.py
mbari_aidata/commands/transform.py
mbari_aidata/common_args.py
mbari_aidata/generators/cifar.py
mbari_aidata/generators/coco_voc.py
mbari_aidata/generators/utils.py
mbari_aidata/logger/__init__.py
mbari_aidata/plugins/extractors/media_types.py
mbari_aidata/plugins/extractors/tap_cfe_media.py
mbari_aidata/plugins/extractors/tap_i2map_media.py
mbari_aidata/plugins/extractors/tap_planktivore_media.py
mbari_aidata/plugins/extractors/tap_sdcat_csv.py
mbari_aidata/plugins/extractors/tap_sony_media.py
mbari_aidata/plugins/extractors/tap_voc.py
mbari_aidata/plugins/loaders/tator/attribute_utils.py
mbari_aidata/plugins/loaders/tator/common.py
mbari_aidata/plugins/loaders/tator/localization.py
mbari_aidata/plugins/loaders/tator/media.py
mbari_aidata/plugins/loaders/tator_redis/consume_localization.py
mbari_aidata/plugins/loaders/tator_redis/consume_media.py
mbari_aidata/plugins/module_utils.py
mbari_aidata/predictors/process_vits.py
mbari_aidata/predictors/vector_similarity.py
mbari_aidata-1.68.0.dist-info/METADATA
mbari_aidata-1.68.0.dist-info/WHEEL
mbari_aidata-1.68.0.dist-info/entry_points.txt
mbari_aidata-1.68.0.dist-info/RECORD
