Metadata-Version: 2.4
Name: mbari-aidata
Version: 1.68.0
Summary: Command line tool to do extract, transform, load and download operations on AI data for a number of projects at MBARI that require detection, clustering or classification workflows.
License: Apache
Author: Danelle Cline
Author-email: dcline@mbari.org
Requires-Python: >=3.10,<3.13
Classifier: License :: Other/Proprietary License
Classifier: Programming Language :: Python :: 3
Classifier: Programming Language :: Python :: 3.10
Classifier: Programming Language :: Python :: 3.11
Classifier: Programming Language :: Python :: 3.12
Requires-Dist: albucore (>=0.0.16)
Requires-Dist: albumentations (>=1.4.15)
Requires-Dist: click (>=8.1.7)
Requires-Dist: ephem (>=4.1.6)
Requires-Dist: moviepy (>=2.1.1)
Requires-Dist: numpy (>=1.24,<2)
Requires-Dist: opencv-contrib-python (==4.11.0.86)
Requires-Dist: pandas (>=2.0,<3.0)
Requires-Dist: pascal-voc-writer (>=0.1.4)
Requires-Dist: piexif (>=1.1.3)
Requires-Dist: pyarrow (>=15.0,<16.0)
Requires-Dist: pytz (>=2024.1)
Requires-Dist: redis (==5.0.7)
Requires-Dist: requests (>=2.32.3)
Requires-Dist: tator (==1.2.3)
Requires-Dist: torch (==2.2.0)
Requires-Dist: torchvision (==0.17.0)
Requires-Dist: tqdm (==4.67.1)
Requires-Dist: transformers (>=4.42.4,<5.0.0)
